transducer/__init__.py
transducer/_util.py
transducer/coop.py
transducer/eager.py
transducer/functional.py
transducer/infrastructure.py
transducer/lazy.py
transducer/lazy_coop.py
transducer/react.py
transducer/reducers.py
transducer/sinks.py
transducer/sources.py
transducer/transducers.py
transducer-0.9.dist-info/DESCRIPTION.rst
transducer-0.9.dist-info/LICENSE.txt
transducer-0.9.dist-info/METADATA
transducer-0.9.dist-info/RECORD
transducer-0.9.dist-info/WHEEL
transducer-0.9.dist-info/metadata.json
transducer-0.9.dist-info/top_level.txt
