Metadata-Version: 2.0
Name: transducer
Version: 0.9
Summary: Transducers, similar to those in Clojure
Home-page: https://github.com/sixty-north/python-transducers
Author: Sixty North AS
Author-email: rob@sixty-north.com
License: MIT License
Keywords: Python,functional
Platform: UNKNOWN
Classifier: Development Status :: 3 - Alpha
Classifier: Programming Language :: Python
Classifier: Programming Language :: Python :: 3.5
Classifier: Programming Language :: Python :: 3.6
Classifier: Environment :: Other Environment
Classifier: Intended Audience :: Developers
Classifier: License :: OSI Approved :: MIT License
Classifier: Operating System :: OS Independent
Classifier: Topic :: Software Development :: Libraries :: Python Modules
Classifier: Topic :: Utilities
